Metadata-Version: 2.1
Name: fileassoc
Version: 0.0.1
Summary: Python fileassoc
Author: r4isy
Author-email: r4isy@kenucheck.xyz
